{
  "template": "https://github.com/cthoyt/cookiecutter-snekpack",
  "commit": "900ef65f0ad637bb02037d8cd66d0fa8436a236c",
  "checkout": null,
  "context": {
    "cookiecutter": {
      "package_name": "orcid_downloader",
      "package_name_stylized": "ORCID Downloader",
      "short_description": "Download and process ORCID in bulk",
      "author_name": "Charles Tapley Hoyt",
      "author_email": "cthoyt@gmail.com",
      "github_organization_name": "cthoyt",
      "github_repository_name": "orcid_downloader",
      "command_line_interface": false,
      "gitlab": false,
      "runner": "tox",
      "__runner": "tox -e",
      "__runner_pip": "tox tox-uv",
      "__runner_tests": "py",
      "__gh_slug": "cthoyt/orcid_downloader",
      "_template": "https://github.com/cthoyt/cookiecutter-snekpack"
    }
  },
  "directory": null
}
